trove/README
trove/__init__.py
trove/rpc.py
trove/version.py
trove/versions.py
trove/backup/__init__.py
trove/backup/models.py
trove/backup/service.py
trove/backup/state.py
trove/backup/views.py
trove/cluster/__init__.py
trove/cluster/models.py
trove/cluster/service.py
trove/cluster/tasks.py
trove/cluster/views.py
trove/cmd/__init__.py
trove/cmd/api.py
trove/cmd/app_wsgi.py
trove/cmd/common.py
trove/cmd/conductor.py
trove/cmd/fakemode.py
trove/cmd/guest.py
trove/cmd/manage.py
trove/cmd/network_driver.py
trove/cmd/status.py
trove/cmd/taskmanager.py
trove/common/__init__.py
trove/common/api.py
trove/common/apischema.py
trove/common/auth.py
trove/common/base_exception.py
trove/common/base_wsgi.py
trove/common/cache.py
trove/common/cfg.py
trove/common/clients.py
trove/common/clients_admin.py
trove/common/configurations.py
trove/common/constants.py
trove/common/context.py
trove/common/crypto_utils.py
trove/common/debug_utils.py
trove/common/exception.py
trove/common/extensions.py
trove/common/glance.py
trove/common/i18n.py
trove/common/limits.py
trove/common/local.py
trove/common/models.py
trove/common/neutron.py
trove/common/notification.py
trove/common/pagination.py
trove/common/pastedeploy.py
trove/common/policy.py
trove/common/profile.py
trove/common/schemata.py
trove/common/serializable_notification.py
trove/common/server_group.py
trove/common/stream_codecs.py
trove/common/swift.py
trove/common/template.py
trove/common/timeutils.py
trove/common/trove_remote.py
trove/common/utils.py
trove/common/views.py
trove/common/wsgi.py
trove/common/xmlutils.py
trove/common/db/__init__.py
trove/common/db/models.py
trove/common/db/cassandra/__init__.py
trove/common/db/cassandra/models.py
trove/common/db/couchdb/__init__.py
trove/common/db/couchdb/models.py
trove/common/db/mongodb/__init__.py
trove/common/db/mongodb/models.py
trove/common/db/mysql/__init__.py
trove/common/db/mysql/data.py
trove/common/db/mysql/models.py
trove/common/db/postgresql/__init__.py
trove-24.0.0.dist-info/AUTHORS
trove-24.0.0.dist-info/LICENSE
trove-24.0.0.dist-info/METADATA
trove-24.0.0.dist-info/WHEEL
trove-24.0.0.dist-info/entry_points.txt
trove-24.0.0.dist-info/pbr.json
trove-24.0.0.dist-info/top_level.txt
trove-24.0.0.dist-info/RECORD
