Metadata-Version: 2.1
Name: trove
Version: 24.0.0
Summary: OpenStack DBaaS
Home-page: https://docs.openstack.org/trove/latest/
Author: OpenStack
Author-email: openstack-discuss@lists.openstack.org
Classifier: Environment :: OpenStack
Classifier: Intended Audience :: Information Technology
Classifier: Intended Audience :: System Administrators
Classifier: License :: OSI Approved :: Apache Software License
Classifier: Operating System :: POSIX :: Linux
Classifier: Programming Language :: Python
Classifier: Programming Language :: Python :: Implementation :: CPython
Classifier: Programming Language :: Python :: 3 :: Only
Classifier: Programming Language :: Python :: 3
Classifier: Programming Language :: Python :: 3.10
Classifier: Programming Language :: Python :: 3.11
Classifier: Programming Language :: Python :: 3.12
Requires-Python: >= 3.10
License-File: LICENSE
License-File: AUTHORS
Requires-Dist: alembic >=1.8.0
Requires-Dist: pbr >=6.0.0
Requires-Dist: eventlet >=0.27.0
Requires-Dist: SQLAlchemy >=1.4.0
Requires-Dist: keystonemiddleware >=4.17.0
Requires-Dist: Routes >=2.3.1
Requires-Dist: WebOb >=1.7.1
Requires-Dist: PasteDeploy >=1.5.0
Requires-Dist: Paste >=2.0.2
Requires-Dist: netaddr >=0.7.18
Requires-Dist: lxml !=3.7.0,>=3.4.1
Requires-Dist: python-novaclient >=9.1.0
Requires-Dist: python-cinderclient >=3.3.0
Requires-Dist: python-keystoneclient >=3.8.0
Requires-Dist: python-swiftclient >=3.2.0
Requires-Dist: python-designateclient >=2.7.0
Requires-Dist: python-neutronclient >=6.7.0
Requires-Dist: python-glanceclient >=2.8.0
Requires-Dist: python-troveclient >=2.2.0
Requires-Dist: jsonschema >=3.2.0
Requires-Dist: Jinja2 >=2.10
Requires-Dist: pexpect !=3.3,>=3.1
Requires-Dist: oslo.config >=6.8.0
Requires-Dist: oslo.context >=4.0.0
Requires-Dist: oslo.i18n >=3.15.3
Requires-Dist: oslo.middleware >=3.31.0
Requires-Dist: oslo.serialization !=2.19.1,>=2.18.0
Requires-Dist: oslo.service !=1.28.1,>=1.24.0
Requires-Dist: oslo.upgradecheck >=1.3.0
Requires-Dist: oslo.utils >=7.0.0
Requires-Dist: oslo.concurrency >=3.26.0
Requires-Dist: PyMySQL >=0.7.6
Requires-Dist: stevedore >=1.20.0
Requires-Dist: oslo.messaging >=14.1.0
Requires-Dist: osprofiler >=1.4.0
Requires-Dist: oslo.log >=3.36.0
Requires-Dist: oslo.db >=4.27.0
Requires-Dist: xmltodict >=0.10.1
Requires-Dist: cryptography >=2.1.4
Requires-Dist: oslo.policy >=4.5.0
Requires-Dist: docker >=4.2.0
Requires-Dist: psycopg2-binary >=2.6.2
Requires-Dist: semantic-version >=2.7.0
Requires-Dist: oslo.cache >=1.26.0
Requires-Dist: Flask >=2.2.3
Requires-Dist: gunicorn >=20.1.0
Requires-Dist: pyroute2 >=0.7.7 ; (sys_platform!='win32')
